crsts/__init__.py
crsts/crsts.py
crstso/__init__.py
crstso/crstso.py
crstso-2.1.5.dist-info/LICENSE
crstso-2.1.5.dist-info/METADATA
crstso-2.1.5.dist-info/WHEEL
crstso-2.1.5.dist-info/top_level.txt
crstso-2.1.5.dist-info/RECORD
