Metadata-Version: 2.1
Name: crstso
Version: 2.1.5
Summary: This is my personal toolkit.
Home-page: https://github.com/wsywddr
Author: Chris Chen
Author-email: wsywddr@163.com
License: UNKNOWN
Platform: UNKNOWN
Classifier: Programming Language :: Python :: 2
Classifier: License :: OSI Approved :: MIT License
Classifier: Operating System :: OS Independent
